{
  "status": 0,
  "result": [
    {
      "createdById": "0052o000008wdskAAA",
      "createdByName": "Yevgen Odokiienko",
      "createdDate": "2019-09-09T23:34:01.000Z",
      "fileName": "reports/unfiled$public/Vacancies_and_candidates.report",
      "fullName": "unfiled$public/Vacancies_and_candidates",
      "id": "00O2o000007Y7gxEAC",
      "lastModifiedById": "0052o000008wdskAAA",
      "lastModifiedByName": "Yevgen Odokiienko",
      "lastModifiedDate": "2019-09-10T09:21:20.000Z",
      "manageableState": "unmanaged",
      "type": "Report"
    },
    {
      "createdById": "0052o000008wdskAAA",
      "createdByName": "Yevgen Odokiienko",
      "createdDate": "2019-09-09T18:00:48.000Z",
      "fileName": "reports/unfiled$public/All_vacancies_by_status.report",
      "fullName": "unfiled$public/All_vacancies_by_status",
      "id": "00O2o000007Y7StEAK",
      "lastModifiedById": "0052o000008wdskAAA",
      "lastModifiedByName": "Yevgen Odokiienko",
      "lastModifiedDate": "2019-09-10T09:21:23.000Z",
      "manageableState": "unmanaged",
      "type": "Report"
    },
    {
      "createdById": "0052o000008wdskAAA",
      "createdByName": "Yevgen Odokiienko",
      "createdDate": "2019-09-09T21:21:01.000Z",
      "fileName": "reports/unfiled$public/Hired_Rate_Report_pOC.report",
      "fullName": "unfiled$public/Hired_Rate_Report_pOC",
      "id": "00O2o000007Y7gTEAS",
      "lastModifiedById": "0052o000008wdskAAA",
      "lastModifiedByName": "Yevgen Odokiienko",
      "lastModifiedDate": "2019-09-10T09:21:26.000Z",
      "manageableState": "unmanaged",
      "type": "Report"
    },
    {
      "createdById": "0052o000008wdskAAA",
      "createdByName": "Yevgen Odokiienko",
      "createdDate": "2019-09-09T16:36:00.000Z",
      "fileName": "reports/unfiled$public/Number_of_candidates_entered.report",
      "fullName": "unfiled$public/Number_of_candidates_entered",
      "id": "00O2o000007Y7KtEAK",
      "lastModifiedById": "0052o000008wdskAAA",
      "lastModifiedByName": "Yevgen Odokiienko",
      "lastModifiedDate": "2019-09-10T09:21:37.000Z",
      "manageableState": "unmanaged",
      "type": "Report"
    },
    {
      "createdById": "0052o000008wdskAAA",
      "createdByName": "Yevgen Odokiienko",
      "createdDate": "2019-09-09T17:15:44.000Z",
      "fileName": "reports/unfiled$public/Number_of_vacancies_closed_by_Recruiter.report",
      "fullName": "unfiled$public/Number_of_vacancies_closed_by_Recruiter",
      "id": "00O2o000007Y7O7EAK",
      "lastModifiedById": "0052o000008wdskAAA",
      "lastModifiedByName": "Yevgen Odokiienko",
      "lastModifiedDate": "2019-09-10T09:21:34.000Z",
      "manageableState": "unmanaged",
      "type": "Report"
    },
    {
      "createdById": "0052o000008wdskAAA",
      "createdByName": "Yevgen Odokiienko",
      "createdDate": "2019-09-09T18:09:20.000Z",
      "fileName": "reports/unfiled$public/Opened_vs_Closed_vacancies.report",
      "fullName": "unfiled$public/Opened_vs_Closed_vacancies",
      "id": "00O2o000007Y7SyEAK",
      "lastModifiedById": "0052o000008wdskAAA",
      "lastModifiedByName": "Yevgen Odokiienko",
      "lastModifiedDate": "2019-09-10T09:21:30.000Z",
      "manageableState": "unmanaged",
      "type": "Report"
    },
    {
      "createdById": "0052o000008wdskAAA",
      "createdByName": "Yevgen Odokiienko",
      "createdDate": "2019-09-09T17:56:53.000Z",
      "fileName": "reports/unfiled$public/Number_of_vacancies_submitted_by_Manager.report",
      "fullName": "unfiled$public/Number_of_vacancies_submitted_by_Manager",
      "id": "00O2o000007Y7SjEAK",
      "lastModifiedById": "0052o000008wdskAAA",
      "lastModifiedByName": "Yevgen Odokiienko",
      "lastModifiedDate": "2019-09-10T09:21:32.000Z",
      "manageableState": "unmanaged",
      "type": "Report"
    }
  ]
}
